par2/__main__.py
par2/cli.py
par2/binaries/par2
par2cmdline_turbo-1.3.0.dist-info/licenses/LICENSE
par2cmdline_turbo-1.3.0.dist-info/METADATA
par2cmdline_turbo-1.3.0.dist-info/WHEEL
par2cmdline_turbo-1.3.0.dist-info/entry_points.txt
par2cmdline_turbo-1.3.0.dist-info/top_level.txt
par2cmdline_turbo-1.3.0.dist-info/RECORD
