Metadata-Version: 2.4
Name: par2cmdline-turbo
Version: 1.3.0
Summary: Produce, verify and repair par2 files.
Author-email: Brent Huisman <brent@huisman.eu.org>
Maintainer-email: Brent Huisman <brent@huisman.eu.org>
License-Expression: GPL-2.0-or-later
Project-URL: Homepage, https://github.com/brenthuisman/par2cmdline-turbo.py
Project-URL: Issues, https://github.com/brenthuisman/par2cmdline-turbo.py/issues
Project-URL: Changelog, https://github.com/brenthuisman/par2cmdline-turbo.py/releases
Classifier: Development Status :: 5 - Production/Stable
Classifier: Environment :: Console
Classifier: Operating System :: Microsoft :: Windows
Classifier: Operating System :: MacOS
Classifier: Operating System :: POSIX :: Linux
Classifier: Programming Language :: Python :: 3
Classifier: Topic :: Utilities
Requires-Python: >=3.8
License-File: LICENSE
Dynamic: license-file
